any_llm_platform_client/__init__.py
any_llm_platform_client/_version.py
any_llm_platform_client/cli.py
any_llm_platform_client/client.py
any_llm_platform_client/crypto.py
any_llm_platform_client/exceptions.py
any_llm_platform_client-0.2.0.dist-info/licenses/LICENSE
any_llm_platform_client-0.2.0.dist-info/METADATA
any_llm_platform_client-0.2.0.dist-info/WHEEL
any_llm_platform_client-0.2.0.dist-info/entry_points.txt
any_llm_platform_client-0.2.0.dist-info/top_level.txt
any_llm_platform_client-0.2.0.dist-info/RECORD
