Metadata-Version: 2.4
Name: any-llm-platform-client
Version: 0.2.0
Summary: Decrypt provider API keys using X25519 sealed box encryption and challenge-response authentication
License: Apache-2.0
Requires-Python: >=3.11
License-File: LICENSE
Requires-Dist: pynacl>=1.6.0
Requires-Dist: httpx>=0.28.0
Requires-Dist: click>=8.1.0
Dynamic: license-file
